khbank/__init__.py
khbank/fortuneo.py
khbank-1.0.0.dist-info/WHEEL
khbank-1.0.0.dist-info/METADATA
khbank-1.0.0.dist-info/RECORD
