Metadata-Version: 2.1
Name: khbank
Version: 1.0.0
Summary: parse bank statement
Author: Khalid
Author-email: khalidck@gmail.com
Requires-Python: >=3.9,<4.0
Classifier: Programming Language :: Python :: 3
Classifier: Programming Language :: Python :: 3.9
Requires-Dist: toolz (>=0.11.1,<0.12.0)
